simple_indian_date/__init__.py
simple_indian_date/convert.py
simple_indian_date-0.1.0.dist-info/LICENSE
simple_indian_date-0.1.0.dist-info/METADATA
simple_indian_date-0.1.0.dist-info/WHEEL
simple_indian_date-0.1.0.dist-info/RECORD
